[
  {"lemma": "Vorratskammer", "pos": "noun", "level": "B2", "freq": 2600, "noun": {"gender": "f", "plural": "Vorratskammern"}, "senses": [{"en": "pantry, storage room", "example_de": "Die Nudeln stehen hinten in der Vorratskammer.", "example_en": "The pasta is at the back of the pantry."}]},
  {"lemma": "Kehrschaufel", "pos": "noun", "level": "B2", "freq": 2800, "noun": {"gender": "f", "plural": "Kehrschaufeln"}, "senses": [{"en": "dustpan", "example_de": "Hol bitte Besen und Kehrschaufel, hier liegen Scherben.", "example_en": "Please get the broom and dustpan, there is broken glass here."}]},
  {"lemma": "Wischmopp", "pos": "noun", "level": "B2", "freq": 2850, "noun": {"gender": "m", "plural": "Wischmopps"}, "senses": [{"en": "mop", "example_de": "Nach dem Frühstück ging sie mit dem Wischmopp durch die Küche.", "example_en": "After breakfast she went over the kitchen with the mop."}]},
  {"lemma": "Putzlappen", "pos": "noun", "level": "B2", "freq": 2700, "noun": {"gender": "m", "plural": "Putzlappen"}, "senses": [{"en": "cleaning rag, cleaning cloth", "example_de": "Der Putzlappen hängt am Wasserhahn.", "example_en": "The cleaning rag is hanging on the tap."}]},
  {"lemma": "Putzmittel", "pos": "noun", "level": "B1", "freq": 2100, "noun": {"gender": "n", "plural": "Putzmittel"}, "senses": [{"en": "cleaning product, cleaning agent", "example_de": "Die Putzmittel stehen unter der Spüle.", "example_en": "The cleaning products are under the sink."}]},
  {"lemma": "Spülmittel", "pos": "noun", "level": "B1", "freq": 2050, "noun": {"gender": "n", "plural": "Spülmittel"}, "senses": [{"en": "dish soap, washing-up liquid", "example_de": "Das Spülmittel ist fast leer, schreib es auf den Zettel.", "example_en": "The dish soap is almost empty, put it on the list."}]},
  {"lemma": "Weichspüler", "pos": "noun", "level": "B2", "freq": 2900, "noun": {"gender": "m", "plural": "Weichspüler"}, "senses": [{"en": "fabric softener", "example_de": "Für Handtücher benutze ich keinen Weichspüler.", "example_en": "I do not use fabric softener for towels."}]},
  {"lemma": "Waschmittel", "pos": "noun", "level": "B1", "freq": 2000, "noun": {"gender": "n", "plural": "Waschmittel"}, "senses": [{"en": "laundry detergent", "example_de": "Dieses Waschmittel riecht nach Lavendel.", "example_en": "This laundry detergent smells of lavender."}]},
  {"lemma": "Fussel", "pos": "noun", "level": "B2", "freq": 2950, "noun": {"gender": "m", "plural": "Fusseln"}, "senses": [{"en": "lint, fluff (on clothes)", "example_de": "Auf dem schwarzen Pullover sieht man jeden Fussel.", "example_en": "You can see every bit of lint on the black sweater."}]},
  {"lemma": "Krümel", "pos": "noun", "level": "B1", "freq": 2300, "noun": {"gender": "m", "plural": "Krümel"}, "senses": [{"en": "crumb", "example_de": "Nach dem Essen lagen überall Krümel auf dem Tisch.", "example_en": "After the meal there were crumbs all over the table."}]},
  {"lemma": "Staubsaugerbeutel", "pos": "noun", "level": "B2", "freq": 2980, "noun": {"gender": "m", "plural": "Staubsaugerbeutel"}, "senses": [{"en": "vacuum cleaner bag", "example_de": "Der Staubsaugerbeutel ist voll und muss gewechselt werden.", "example_en": "The vacuum cleaner bag is full and needs to be changed."}]},
  {"lemma": "Verlängerungskabel", "pos": "noun", "level": "B2", "freq": 2750, "noun": {"gender": "n", "plural": "Verlängerungskabel"}, "senses": [{"en": "extension cord", "example_de": "Ohne Verlängerungskabel reicht das Kabel nicht bis zur Lampe.", "example_en": "Without an extension cord the cable does not reach the lamp."}]},
  {"lemma": "Mehrfachsteckdose", "pos": "noun", "level": "B2", "freq": 2960, "noun": {"gender": "f", "plural": "Mehrfachsteckdosen"}, "senses": [{"en": "power strip, multi-socket adapter", "example_de": "Am Schreibtisch hängt alles an einer Mehrfachsteckdose.", "example_en": "At the desk everything is plugged into one power strip."}]},
  {"lemma": "Abfluss", "pos": "noun", "level": "B2", "freq": 2500, "noun": {"gender": "m", "plural": "Abflüsse"}, "senses": [{"en": "drain", "example_de": "Der Abfluss in der Dusche ist schon wieder verstopft.", "example_en": "The drain in the shower is blocked again."}]},
  {"lemma": "Sicherung", "pos": "noun", "level": "B2", "freq": 2650, "noun": {"gender": "f", "plural": "Sicherungen"}, "senses": [{"en": "fuse, circuit breaker", "note": "die Sicherung ist rausgeflogen = the fuse blew", "example_de": "Beim Föhnen ist die Sicherung rausgeflogen.", "example_en": "The fuse blew while I was drying my hair."}]},
  {"lemma": "Zählerstand", "pos": "noun", "level": "B2", "freq": 2900, "noun": {"gender": "m", "plural": "Zählerstände"}, "senses": [{"en": "meter reading", "example_de": "Bitte teilen Sie uns bis Freitag den Zählerstand mit.", "example_en": "Please send us the meter reading by Friday."}]},
  {"lemma": "Stromverbrauch", "pos": "noun", "level": "B2", "freq": 2700, "noun": {"gender": "m", "plural": null}, "senses": [{"en": "electricity consumption, power usage", "example_de": "Der neue Kühlschrank hat einen viel niedrigeren Stromverbrauch.", "example_en": "The new fridge has a much lower electricity consumption."}]},
  {"lemma": "Heizkosten", "pos": "noun", "level": "B2", "freq": 2600, "noun": {"gender": "pl", "plural": null}, "senses": [{"en": "heating costs", "example_de": "Im Winter steigen unsere Heizkosten stark.", "example_en": "In winter our heating costs rise sharply."}]},
  {"lemma": "Thermostat", "pos": "noun", "level": "B2", "freq": 2850, "noun": {"gender": "m", "plural": "Thermostate"}, "senses": [{"en": "thermostat", "example_de": "Stell das Thermostat nachts auf eine niedrige Stufe.", "example_en": "Set the thermostat to a low level at night."}]},
  {"lemma": "Schimmel", "pos": "noun", "level": "B2", "freq": 2400, "noun": {"gender": "m", "plural": null}, "senses": [{"en": "mould, mildew", "example_de": "In der Ecke des Badezimmers bildet sich Schimmel.", "example_en": "Mould is forming in the corner of the bathroom."}]},
  {"lemma": "Zugluft", "pos": "noun", "level": "B2", "freq": 2950, "noun": {"gender": "f", "plural": null}, "senses": [{"en": "draught, draft (of cold air)", "example_de": "Durch das alte Fenster kommt unangenehme Zugluft.", "example_en": "An unpleasant draught comes through the old window."}]},
  {"lemma": "Rollladen", "pos": "noun", "level": "B2", "freq": 2800, "noun": {"gender": "m", "plural": "Rollläden"}, "senses": [{"en": "roller shutter", "example_de": "Abends lassen wir die Rollläden herunter.", "example_en": "In the evening we let down the roller shutters."}]},
  {"lemma": "Jalousie", "pos": "noun", "level": "B2", "freq": 2820, "noun": {"gender": "f", "plural": "Jalousien"}, "senses": [{"en": "venetian blind", "example_de": "Bei Sonne schließe ich die Jalousie im Büro.", "example_en": "When it is sunny I close the blind in the office."}]},
  {"lemma": "Fensterbank", "pos": "noun", "level": "B1", "freq": 2450, "noun": {"gender": "f", "plural": "Fensterbänke"}, "senses": [{"en": "windowsill", "example_de": "Auf der Fensterbank stehen kleine Pflanzen.", "example_en": "There are small plants on the windowsill."}]},
  {"lemma": "Lichtschalter", "pos": "noun", "level": "B1", "freq": 2350, "noun": {"gender": "m", "plural": "Lichtschalter"}, "senses": [{"en": "light switch", "example_de": "Der Lichtschalter ist links neben der Tür.", "example_en": "The light switch is to the left of the door."}]},
  {"lemma": "Türklinke", "pos": "noun", "level": "B2", "freq": 2550, "noun": {"gender": "f", "plural": "Türklinken"}, "senses": [{"en": "door handle", "example_de": "Die Türklinke ist locker und muss festgeschraubt werden.", "example_en": "The door handle is loose and needs to be screwed tight."}]},
  {"lemma": "Türschloss", "pos": "noun", "level": "B1", "freq": 2500, "noun": {"gender": "n", "plural": "Türschlösser"}, "senses": [{"en": "door lock", "example_de": "Der Schlüssel steckt im Türschloss fest.", "example_en": "The key is stuck in the door lock."}]},
  {"lemma": "Ersatzschlüssel", "pos": "noun", "level": "B2", "freq": 2750, "noun": {"gender": "m", "plural": "Ersatzschlüssel"}, "senses": [{"en": "spare key", "example_de": "Die Nachbarin hat einen Ersatzschlüssel für unsere Wohnung.", "example_en": "The neighbour has a spare key for our apartment."}]},
  {"lemma": "Schlüsseldienst", "pos": "noun", "level": "B2", "freq": 2850, "noun": {"gender": "m", "plural": "Schlüsseldienste"}, "senses": [{"en": "locksmith service", "example_de": "Ich stand vor verschlossener Tür und musste den Schlüsseldienst rufen.", "example_en": "I was locked out and had to call the locksmith service."}]},
  {"lemma": "Fußmatte", "pos": "noun", "level": "B2", "freq": 2700, "noun": {"gender": "f", "plural": "Fußmatten"}, "senses": [{"en": "doormat", "example_de": "Bitte die Schuhe auf der Fußmatte abtreten.", "example_en": "Please wipe your shoes on the doormat."}]},
  {"lemma": "Wäscheständer", "pos": "noun", "level": "B2", "freq": 2650, "noun": {"gender": "m", "plural": "Wäscheständer"}, "senses": [{"en": "clothes drying rack", "example_de": "Der Wäscheständer steht zum Trocknen auf dem Balkon.", "example_en": "The drying rack is on the balcony for drying."}]},
  {"lemma": "Wäscheklammer", "pos": "noun", "level": "B1", "freq": 2600, "noun": {"gender": "f", "plural": "Wäscheklammern"}, "senses": [{"en": "clothes peg, clothespin", "example_de": "Mir fehlen zwei Wäscheklammern für die Handtücher.", "example_en": "I am missing two clothes pegs for the towels."}]},
  {"lemma": "Wäschekorb", "pos": "noun", "level": "B1", "freq": 2550, "noun": {"gender": "m", "plural": "Wäschekörbe"}, "senses": [{"en": "laundry basket", "example_de": "Der Wäschekorb ist schon wieder voll.", "example_en": "The laundry basket is full again."}]},
  {"lemma": "Wäscheleine", "pos": "noun", "level": "B1", "freq": 2620, "noun": {"gender": "f", "plural": "Wäscheleinen"}, "senses": [{"en": "clothesline", "example_de": "Die Bettwäsche hängt draußen auf der Wäscheleine.", "example_en": "The bed linen is hanging outside on the clothesline."}]},
  {"lemma": "Bügelbrett", "pos": "noun", "level": "B1", "freq": 2580, "noun": {"gender": "n", "plural": "Bügelbretter"}, "senses": [{"en": "ironing board", "example_de": "Stell das Bügelbrett bitte wieder in den Schrank.", "example_en": "Please put the ironing board back in the closet."}]},
  {"lemma": "Frühjahrsputz", "pos": "noun", "level": "B2", "freq": 2900, "noun": {"gender": "m", "plural": null}, "senses": [{"en": "spring cleaning", "example_de": "Beim Frühjahrsputz haben wir den ganzen Keller ausgeräumt.", "example_en": "During spring cleaning we cleared out the whole cellar."}]},
  {"lemma": "Haushaltshilfe", "pos": "noun", "level": "B2", "freq": 2750, "noun": {"gender": "f", "plural": "Haushaltshilfen"}, "senses": [{"en": "domestic help, cleaner", "example_de": "Seit der Geburt des Kindes haben sie eine Haushaltshilfe.", "example_en": "Since the birth of the child they have had domestic help."}]},
  {"lemma": "Verbandskasten", "pos": "noun", "level": "B2", "freq": 2800, "noun": {"gender": "m", "plural": "Verbandskästen"}, "senses": [{"en": "first-aid kit", "example_de": "Im Auto muss immer ein Verbandskasten liegen.", "example_en": "There must always be a first-aid kit in the car."}]},
  {"lemma": "Hausapotheke", "pos": "noun", "level": "B2", "freq": 2850, "noun": {"gender": "f", "plural": "Hausapotheken"}, "senses": [{"en": "medicine cabinet, home medical supplies", "example_de": "Schmerztabletten gehören in jede Hausapotheke.", "example_en": "Painkillers belong in every medicine cabinet."}]},
  {"lemma": "Brotdose", "pos": "noun", "level": "B1", "freq": 2400, "noun": {"gender": "f", "plural": "Brotdosen"}, "senses": [{"en": "lunch box", "example_de": "Sie packt jeden Morgen die Brotdose für ihre Tochter.", "example_en": "Every morning she packs the lunch box for her daughter."}]},
  {"lemma": "Frischhaltefolie", "pos": "noun", "level": "B2", "freq": 2780, "noun": {"gender": "f", "plural": "Frischhaltefolien"}, "senses": [{"en": "cling film, plastic wrap", "example_de": "Deck den Salat mit Frischhaltefolie ab.", "example_en": "Cover the salad with cling film."}]},
  {"lemma": "Haltbarkeitsdatum", "pos": "noun", "level": "B2", "freq": 2500, "noun": {"gender": "n", "plural": "Haltbarkeitsdaten"}, "senses": [{"en": "best-before date, expiry date", "example_de": "Prüf vor dem Kochen das Haltbarkeitsdatum auf der Packung.", "example_en": "Check the best-before date on the package before cooking."}]},
  {"lemma": "Aufstrich", "pos": "noun", "level": "B2", "freq": 2720, "noun": {"gender": "m", "plural": "Aufstriche"}, "senses": [{"en": "spread (for bread)", "example_de": "Zum Frühstück gibt es Brot mit verschiedenen Aufstrichen.", "example_en": "For breakfast there is bread with different spreads."}]},
  {"lemma": "Konserve", "pos": "noun", "level": "B1", "freq": 2460, "noun": {"gender": "f", "plural": "Konserven"}, "senses": [{"en": "canned food, tin", "example_de": "Für den Notfall haben wir ein paar Konserven im Schrank.", "example_en": "For emergencies we have a few cans in the cupboard."}]},
  {"lemma": "Sparschäler", "pos": "noun", "level": "B2", "freq": 2990, "noun": {"gender": "m", "plural": "Sparschäler"}, "senses": [{"en": "vegetable peeler", "example_de": "Mit dem Sparschäler geht das Kartoffelschälen viel schneller.", "example_en": "With the peeler, peeling potatoes is much faster."}]},
  {"lemma": "Auflaufform", "pos": "noun", "level": "B2", "freq": 2870, "noun": {"gender": "f", "plural": "Auflaufformen"}, "senses": [{"en": "casserole dish, baking dish", "example_de": "Gib die Nudeln mit der Soße in eine Auflaufform.", "example_en": "Put the pasta with the sauce into a casserole dish."}]},
  {"lemma": "Spülbecken", "pos": "noun", "level": "B2", "freq": 2560, "noun": {"gender": "n", "plural": "Spülbecken"}, "senses": [{"en": "kitchen sink", "example_de": "Das schmutzige Geschirr stapelt sich im Spülbecken.", "example_en": "The dirty dishes are piling up in the sink."}]},
  {"lemma": "Geschirrtuch", "pos": "noun", "level": "B1", "freq": 2440, "noun": {"gender": "n", "plural": "Geschirrtücher"}, "senses": [{"en": "tea towel, dish towel", "example_de": "Trockne die Gläser mit einem sauberen Geschirrtuch ab.", "example_en": "Dry the glasses with a clean tea towel."}]},
  {"lemma": "Küchenrolle", "pos": "noun", "level": "B2", "freq": 2680, "noun": {"gender": "f", "plural": "Küchenrollen"}, "senses": [{"en": "kitchen roll, paper towels", "example_de": "Wisch den Saft schnell mit Küchenrolle auf.", "example_en": "Quickly wipe up the juice with paper towels."}]},
  {"lemma": "Müllbeutel", "pos": "noun", "level": "B1", "freq": 2380, "noun": {"gender": "m", "plural": "Müllbeutel"}, "senses": [{"en": "bin bag, garbage bag", "example_de": "Kannst du einen neuen Müllbeutel in den Eimer machen?", "example_en": "Can you put a new bin bag in the bin?"}]},
  {"lemma": "Stauraum", "pos": "noun", "level": "B2", "freq": 2740, "noun": {"gender": "m", "plural": "Stauräume"}, "senses": [{"en": "storage space", "example_de": "Die kleine Wohnung hat leider wenig Stauraum.", "example_en": "Unfortunately the small apartment has little storage space."}]},
  {"lemma": "Krimskrams", "pos": "noun", "level": "B2", "freq": 2970, "noun": {"gender": "m", "plural": null, "genitive": "Krimskrams"}, "senses": [{"en": "odds and ends, knick-knacks", "example_de": "In der Schublade liegt nur alter Krimskrams.", "example_en": "There are only old odds and ends in the drawer."}]},
  {"lemma": "Gerümpel", "pos": "noun", "level": "B2", "freq": 2880, "noun": {"gender": "n", "plural": null}, "senses": [{"en": "junk, clutter", "example_de": "Der Dachboden ist voller Gerümpel.", "example_en": "The attic is full of junk."}]},
  {"lemma": "Sperrmüll", "pos": "noun", "level": "B2", "freq": 2600, "noun": {"gender": "m", "plural": null}, "senses": [{"en": "bulky waste", "example_de": "Das alte Sofa stellen wir zum Sperrmüll.", "example_en": "We are putting the old sofa out with the bulky waste."}]},
  {"lemma": "Altglas", "pos": "noun", "level": "B2", "freq": 2760, "noun": {"gender": "n", "plural": null}, "senses": [{"en": "waste glass, glass for recycling", "example_de": "Ich bringe das Altglas zum Container an der Ecke.", "example_en": "I take the waste glass to the container on the corner."}]},
  {"lemma": "Restmüll", "pos": "noun", "level": "B2", "freq": 2540, "noun": {"gender": "m", "plural": null}, "senses": [{"en": "residual waste, general waste", "example_de": "Windeln gehören in den Restmüll.", "example_en": "Nappies belong in the general waste."}]},
  {"lemma": "Biomüll", "pos": "noun", "level": "B2", "freq": 2520, "noun": {"gender": "m", "plural": null}, "senses": [{"en": "organic waste", "example_de": "Kaffeesatz und Schalen kommen in den Biomüll.", "example_en": "Coffee grounds and peels go into the organic waste."}]},
  {"lemma": "Leergut", "pos": "noun", "level": "B2", "freq": 2790, "noun": {"gender": "n", "plural": null}, "senses": [{"en": "empties, returnable bottles", "example_de": "Bring das Leergut bitte zum Supermarkt zurück.", "example_en": "Please take the empties back to the supermarket."}]}
]
